CMakeLists.txt
LICENSE
MANIFEST.in
README.txt
setup.cfg
setup.py
cmake/FindCython.cmake
cmake/ReplicatePythonSourceTree.cmake
cmake/UseCython.cmake
cmake/zq.cmake
modules/CheetahTemplate.py
modules/Demo.py
modules/Version.py
querylib/DeleteHostGroup.zql
querylib/DisplayStack.zql
querylib/LoopDemo1.zql
querylib/ReportError.zql
querylib/ReportOk.zql
querylib/SelectHostgroup.zql
templates/hostgroups.tpl
zq/CMakeLists.txt
zq/__init__.py
zq/zq.pyx
zq/zq_args.pyx
zq/zq_bjq.pyx
zq/zq_cache_of_files.pyx
zq/zq_cfg.pyx
zq/zq_clear.pyx
zq/zq_cmd.pyx
zq/zq_cmd_batch.pyx
zq/zq_cmd_eval.pyx
zq/zq_cmd_exec.pyx
zq/zq_cmd_query.pyx
zq/zq_env.pyx
zq/zq_env_modcache.pyx
zq/zq_expiringdict.pyx
zq/zq_ext_gen.pyx
zq/zq_ext_time.pyx
zq/zq_func.pyx
zq/zq_lib.pyx
zq/zq_modules.pyx
zq/zq_pyzabbix.pyx
zq/zq_query.pyx
zq/zq_query_application.pyx
zq/zq_query_create.pyx
zq/zq_query_create_host_supplimental.pyx
zq/zq_query_delete.pyx
zq/zq_query_display.pyx
zq/zq_query_extern.pyx
zq/zq_query_filters.pyx
zq/zq_query_group.pyx
zq/zq_query_join.pyx
zq/zq_query_link.pyx
zq/zq_query_logic.pyx
zq/zq_query_loop.pyx
zq/zq_query_new.pyx
zq/zq_query_output.pyx
zq/zq_query_query.pyx
zq/zq_query_stack.pyx
zq/zq_query_stackless.pyx
zq/zq_query_status.pyx
zq/zq_query_update.pyx
zq/zq_query_vars.pyx
zq/zq_query_words.pyx
zq/zq_symbols.pyx
zq/zq_terminal.pyx
zq/zql.pyx
zq.egg-info/PKG-INFO
zq.egg-info/SOURCES.txt
zq.egg-info/dependency_links.txt
zq.egg-info/not-zip-safe
zq.egg-info/requires.txt
zq.egg-info/top_level.txt