Metadata-Version: 1.1
Name: zq
Version: 0.6
Summary: ZQL - Zabbix Query Language
Home-page: https://github.com/vulogov/zq/
Author: Vladimir Ulogov
Author-email: vladimir.ulogov@me.com
License: GNU GPL Versin 3
Keywords: zql,monitoring,zabbix
Platform: GNU/Linux
Platform: Unix
Platform: Mac OS-X
Classifier: Development Status :: 3 - Alpha
Classifier: Intended Audience :: Developers
Classifier: Intended Audience :: Information Technology
Classifier: License :: OSI Approved :: GNU General Public License v3 (GPLv3)
Classifier: Operating System :: OS Independent
Classifier: Programming Language :: Python :: 2
Classifier: Programming Language :: Python :: 2.6
Classifier: Programming Language :: Python :: 2.7
Classifier: Topic :: Software Development
Classifier: Topic :: Software Development :: Libraries
Classifier: Topic :: Software Development :: Libraries :: Python Modules
Classifier: Topic :: Software Development :: Libraries :: Python Modules
Classifier: Topic :: System :: Monitoring
Classifier: Topic :: System :: Networking :: Monitoring
Classifier: Topic :: System :: Systems Administration
Classifier: Environment :: Console
Classifier: Environment :: Console :: Curses
